pytcli/__debug__.py
pytcli/__init__.py
pytcli-1.0.0.dist-info/LICENSE
pytcli-1.0.0.dist-info/METADATA
pytcli-1.0.0.dist-info/WHEEL
pytcli-1.0.0.dist-info/top_level.txt
pytcli-1.0.0.dist-info/RECORD
