Metadata-Version: 2.1
Name: pytcli
Version: 1.0.0
Summary: This is a pytcli. (A command line for python toollib package)
Home-page: https://github.com/atpuxiner/pytcli
Author: axiner
Author-email: atpuxiner@163.com
License: MIT
Platform: any
Classifier: License :: OSI Approved :: MIT License
Classifier: Operating System :: OS Independent
Classifier: Programming Language :: Python :: 3
Requires-Python: >=3.7
License-File: LICENSE
Requires-Dist: toollib
